wampproto/__init__.py
wampproto/acceptor.py
wampproto/broker.py
wampproto/dealer.py
wampproto/exception.py
wampproto/idgen.py
wampproto/joiner.py
wampproto/session.py
wampproto/types.py
wampproto/uris.py
wampproto/auth/__init__.py
wampproto/auth/anonymous.py
wampproto/auth/auth.py
wampproto/auth/cryptosign.py
wampproto/auth/ticket.py
wampproto/auth/wampcra.py
wampproto/messages/__init__.py
wampproto/messages/abort.py
wampproto/messages/authenticate.py
wampproto/messages/call.py
wampproto/messages/cancel.py
wampproto/messages/challenge.py
wampproto/messages/error.py
wampproto/messages/event.py
wampproto/messages/exceptions.py
wampproto/messages/goodbye.py
wampproto/messages/hello.py
wampproto/messages/interrupt.py
wampproto/messages/invocation.py
wampproto/messages/message.py
wampproto/messages/publish.py
wampproto/messages/published.py
wampproto/messages/register.py
wampproto/messages/registered.py
wampproto/messages/result.py
wampproto/messages/subscribe.py
wampproto/messages/subscribed.py
wampproto/messages/unregister.py
wampproto/messages/unregistered.py
wampproto/messages/unsubscribe.py
wampproto/messages/unsubscribed.py
wampproto/messages/util.py
wampproto/messages/validation_spec.py
wampproto/messages/welcome.py
wampproto/messages/yield_.py
wampproto/serializers/__init__.py
wampproto/serializers/cbor.py
wampproto/serializers/json.py
wampproto/serializers/msgpack.py
wampproto/serializers/payload.py
wampproto/serializers/serializer.py
wampproto/transports/__init__.py
wampproto/transports/rawsocket.py
wampproto-0.4.0.dist-info/licenses/LICENSE
wampproto-0.4.0.dist-info/METADATA
wampproto-0.4.0.dist-info/WHEEL
wampproto-0.4.0.dist-info/top_level.txt
wampproto-0.4.0.dist-info/RECORD
