Metadata-Version: 2.4
Name: wampproto
Version: 0.4.0
Summary: https://github.com/xconnio/wampproto-python
Author-email: Omer Akram <omer@xconn.io>, Mahad Munir <mahad@xconn.io>
Project-URL: Homepage, https://github.com/xconnio/wampproto-python
Project-URL: Bug Tracker, https://github.com/xconnio/wampproto-python/issues
Classifier: Development Status :: 4 - Beta
Classifier: Programming Language :: Python :: 3.10
Classifier: Programming Language :: Python :: 3.11
Classifier: Programming Language :: Python :: 3.12
Classifier: Programming Language :: Python :: 3.13
Requires-Python: >=3.10
License-File: LICENSE
Requires-Dist: cbor2
Requires-Dist: msgpack
Requires-Dist: pynacl
Provides-Extra: test
Requires-Dist: coverage; extra == "test"
Requires-Dist: pytest; extra == "test"
Requires-Dist: ruff; extra == "test"
Requires-Dist: pytest-asyncio; extra == "test"
Dynamic: license-file
